COPYING
MANIFEST.in
README
setup.py
colly/__init__.py
colly/core.py
colly/exceptions.py
colly/optbase.py
colly/test.py
colly.egg-info/PKG-INFO
colly.egg-info/SOURCES.txt
colly.egg-info/dependency_links.txt
colly.egg-info/entry_points.txt
colly.egg-info/requires.txt
colly.egg-info/top_level.txt
colly/commands/__init__.py
colly/commands/diff.py
colly/commands/dummy.py
colly/commands/format.py
colly/commands/help.py
colly/commands/mod.py