Metadata-Version: 1.1
Name: colly
Version: 0.2.1
Summary: Colly - mucky pup; util for making comparison between large CSVs/ data dumps.
